dufflebag/__init__.py
dufflebag-0.1.1.dist-info/METADATA
dufflebag-0.1.1.dist-info/WHEEL
dufflebag-0.1.1.dist-info/top_level.txt
dufflebag-0.1.1.dist-info/RECORD
