Metadata-Version: 2.1
Name: dufflebag
Version: 0.1.1
Summary: packed python utilities in duffle bag
Home-page: UNKNOWN
Author: YeongHyeon Park
Author-email: young200405@gmail.com
License: UNKNOWN
Keywords: dufflebag,duffle-bag
Platform: UNKNOWN
Classifier: Programming Language :: Python :: 3
Requires-Python: >=3
Requires-Dist: numpy
Requires-Dist: scipy
Requires-Dist: tensorflow
